{
  "mainAssemblyName": "TTVLWeb.Game",
  "resources": {
    "hash": "sha256-OweewE/tNT1vhkwT77kYJBYVNDR12u1AoeozLgrsAro=",
    "fingerprinting": {
      "Blazored.LocalStorage.12n6dz54qr.wasm": "Blazored.LocalStorage.wasm",
      "CurrieTechnologies.Razor.SweetAlert2.lvj7kgyo2r.wasm": "CurrieTechnologies.Razor.SweetAlert2.wasm",
      "Ical.Net.anem8fmkmz.wasm": "Ical.Net.wasm",
      "Markdig.hc946gumly.wasm": "Markdig.wasm",
      "Microsoft.AspNetCore.Authorization.cfbh8icicc.wasm": "Microsoft.AspNetCore.Authorization.wasm",
      "Microsoft.AspNetCore.Components.6a500y5mh6.wasm": "Microsoft.AspNetCore.Components.wasm",
      "Microsoft.AspNetCore.Components.Authorization.8idgsl1q3y.wasm": "Microsoft.AspNetCore.Components.Authorization.wasm",
      "Microsoft.AspNetCore.Components.Forms.tro8u9xo1t.wasm": "Microsoft.AspNetCore.Components.Forms.wasm",
      "Microsoft.AspNetCore.Components.Web.ieypenth0x.wasm": "Microsoft.AspNetCore.Components.Web.wasm",
      "Microsoft.AspNetCore.Components.WebAssembly.cppeh7k1y5.wasm": "Microsoft.AspNetCore.Components.WebAssembly.wasm",
      "Microsoft.AspNetCore.Connections.Abstractions.upo8amdyii.wasm": "Microsoft.AspNetCore.Connections.Abstractions.wasm",
      "Microsoft.AspNetCore.Http.Connections.Client.ytkjx15092.wasm": "Microsoft.AspNetCore.Http.Connections.Client.wasm",
      "Microsoft.AspNetCore.Http.Connections.Common.fanq0woy4f.wasm": "Microsoft.AspNetCore.Http.Connections.Common.wasm",
      "Microsoft.AspNetCore.Metadata.kb2pnhxx9n.wasm": "Microsoft.AspNetCore.Metadata.wasm",
      "Microsoft.AspNetCore.SignalR.Client.ck3fgmy7ic.wasm": "Microsoft.AspNetCore.SignalR.Client.wasm",
      "Microsoft.AspNetCore.SignalR.Client.Core.nmrfixdid2.wasm": "Microsoft.AspNetCore.SignalR.Client.Core.wasm",
      "Microsoft.AspNetCore.SignalR.Common.vzsbdkzbkw.wasm": "Microsoft.AspNetCore.SignalR.Common.wasm",
      "Microsoft.AspNetCore.SignalR.Protocols.Json.vbb2g0mdls.wasm": "Microsoft.AspNetCore.SignalR.Protocols.Json.wasm",
      "Microsoft.AspNetCore.WebUtilities.lvjk3wue0z.wasm": "Microsoft.AspNetCore.WebUtilities.wasm",
      "Microsoft.Extensions.Caching.Abstractions.8fsdtwddal.wasm": "Microsoft.Extensions.Caching.Abstractions.wasm",
      "Microsoft.Extensions.Caching.Memory.q4n4ipze2x.wasm": "Microsoft.Extensions.Caching.Memory.wasm",
      "Microsoft.Extensions.Configuration.vplowthuc6.wasm": "Microsoft.Extensions.Configuration.wasm",
      "Microsoft.Extensions.Configuration.Abstractions.kpz8485frw.wasm": "Microsoft.Extensions.Configuration.Abstractions.wasm",
      "Microsoft.Extensions.Configuration.Json.nplwh1dtgg.wasm": "Microsoft.Extensions.Configuration.Json.wasm",
      "Microsoft.Extensions.DependencyInjection.nm0fxb68vu.wasm": "Microsoft.Extensions.DependencyInjection.wasm",
      "Microsoft.Extensions.DependencyInjection.Abstractions.vy92lhoa2e.wasm": "Microsoft.Extensions.DependencyInjection.Abstractions.wasm",
      "Microsoft.Extensions.Diagnostics.lk2ttr0x6l.wasm": "Microsoft.Extensions.Diagnostics.wasm",
      "Microsoft.Extensions.Diagnostics.Abstractions.o97u05c9gb.wasm": "Microsoft.Extensions.Diagnostics.Abstractions.wasm",
      "Microsoft.Extensions.Features.mx2fvizm2n.wasm": "Microsoft.Extensions.Features.wasm",
      "Microsoft.Extensions.Http.b4829cflxg.wasm": "Microsoft.Extensions.Http.wasm",
      "Microsoft.Extensions.Localization.bvn14pws96.wasm": "Microsoft.Extensions.Localization.wasm",
      "Microsoft.Extensions.Localization.Abstractions.ixsppbtym0.wasm": "Microsoft.Extensions.Localization.Abstractions.wasm",
      "Microsoft.Extensions.Logging.d5759dgs08.wasm": "Microsoft.Extensions.Logging.wasm",
      "Microsoft.Extensions.Logging.Abstractions.32sdguicee.wasm": "Microsoft.Extensions.Logging.Abstractions.wasm",
      "Microsoft.Extensions.Options.cye6fgpn51.wasm": "Microsoft.Extensions.Options.wasm",
      "Microsoft.Extensions.Primitives.wdgxpgsqcr.wasm": "Microsoft.Extensions.Primitives.wasm",
      "Microsoft.JSInterop.0hi1zeigqe.wasm": "Microsoft.JSInterop.wasm",
      "Microsoft.JSInterop.WebAssembly.8eb000j8w7.wasm": "Microsoft.JSInterop.WebAssembly.wasm",
      "MudBlazor.bha5kpi6mp.wasm": "MudBlazor.wasm",
      "MudBlazor.Markdown.4m136gm5xx.wasm": "MudBlazor.Markdown.wasm",
      "Newtonsoft.Json.jcjjiqe038.wasm": "Newtonsoft.Json.wasm",
      "NodaTime.nqaqt3vwyv.wasm": "NodaTime.wasm",
      "System.Net.ServerSentEvents.nnx0l54pbx.wasm": "System.Net.ServerSentEvents.wasm",
      "TimeZoneConverter.gpao39u6us.wasm": "TimeZoneConverter.wasm",
      "TinyMCE.Blazor.w2jy6xgyg6.wasm": "TinyMCE.Blazor.wasm",
      "Microsoft.CSharp.g3k0wohq6w.wasm": "Microsoft.CSharp.wasm",
      "System.Collections.Concurrent.jt6m6ckwzx.wasm": "System.Collections.Concurrent.wasm",
      "System.Collections.Immutable.yi2oz8nx9e.wasm": "System.Collections.Immutable.wasm",
      "System.Collections.NonGeneric.x9d02l8h8m.wasm": "System.Collections.NonGeneric.wasm",
      "System.Collections.Specialized.ilumsknp4t.wasm": "System.Collections.Specialized.wasm",
      "System.Collections.04nucowagr.wasm": "System.Collections.wasm",
      "System.ComponentModel.Annotations.f8jtdc89up.wasm": "System.ComponentModel.Annotations.wasm",
      "System.ComponentModel.Primitives.ailars334u.wasm": "System.ComponentModel.Primitives.wasm",
      "System.ComponentModel.TypeConverter.4skrkh1bqm.wasm": "System.ComponentModel.TypeConverter.wasm",
      "System.ComponentModel.zy0ms90z2w.wasm": "System.ComponentModel.wasm",
      "System.Console.9yrfyxte0s.wasm": "System.Console.wasm",
      "System.Data.Common.9xt275crlm.wasm": "System.Data.Common.wasm",
      "System.Diagnostics.DiagnosticSource.xcz565ccv4.wasm": "System.Diagnostics.DiagnosticSource.wasm",
      "System.Diagnostics.TraceSource.hu6e7hj53s.wasm": "System.Diagnostics.TraceSource.wasm",
      "System.Drawing.Primitives.m5nrd9qy4x.wasm": "System.Drawing.Primitives.wasm",
      "System.Drawing.l99g11my7u.wasm": "System.Drawing.wasm",
      "System.IO.Compression.sjtk9axw4l.wasm": "System.IO.Compression.wasm",
      "System.IO.Pipelines.m2d449jl69.wasm": "System.IO.Pipelines.wasm",
      "System.Linq.Expressions.s0aletdlow.wasm": "System.Linq.Expressions.wasm",
      "System.Linq.qrzytruudr.wasm": "System.Linq.wasm",
      "System.Memory.xnia7qknfj.wasm": "System.Memory.wasm",
      "System.Net.Http.Json.4oq6hi5mhk.wasm": "System.Net.Http.Json.wasm",
      "System.Net.Http.42xwngdu5k.wasm": "System.Net.Http.wasm",
      "System.Net.Primitives.zdik3pzjmm.wasm": "System.Net.Primitives.wasm",
      "System.Net.Requests.yocwx48fyv.wasm": "System.Net.Requests.wasm",
      "System.Net.Security.qgtt234y95.wasm": "System.Net.Security.wasm",
      "System.Net.WebSockets.Client.nixn8871fv.wasm": "System.Net.WebSockets.Client.wasm",
      "System.Net.WebSockets.fn5g89hpim.wasm": "System.Net.WebSockets.wasm",
      "System.ObjectModel.v49pg873bw.wasm": "System.ObjectModel.wasm",
      "System.Private.Uri.7sunc304g0.wasm": "System.Private.Uri.wasm",
      "System.Private.Xml.Linq.4428h436dt.wasm": "System.Private.Xml.Linq.wasm",
      "System.Private.Xml.8ut53fck6h.wasm": "System.Private.Xml.wasm",
      "System.Reflection.Emit.ILGeneration.mi2i2v6pwe.wasm": "System.Reflection.Emit.ILGeneration.wasm",
      "System.Reflection.Emit.Lightweight.6xjxglsw9x.wasm": "System.Reflection.Emit.Lightweight.wasm",
      "System.Reflection.Primitives.rm6pev6x7c.wasm": "System.Reflection.Primitives.wasm",
      "System.Runtime.InteropServices.JavaScript.scprsuo250.wasm": "System.Runtime.InteropServices.JavaScript.wasm",
      "System.Runtime.InteropServices.ukm0e9w85b.wasm": "System.Runtime.InteropServices.wasm",
      "System.Runtime.Numerics.xqz3ca6hpg.wasm": "System.Runtime.Numerics.wasm",
      "System.Runtime.Serialization.Formatters.3zc8j22ytb.wasm": "System.Runtime.Serialization.Formatters.wasm",
      "System.Runtime.Serialization.Primitives.zoxiyt80jv.wasm": "System.Runtime.Serialization.Primitives.wasm",
      "System.Runtime.p2j64qg7s2.wasm": "System.Runtime.wasm",
      "System.Security.Claims.ywb828g33q.wasm": "System.Security.Claims.wasm",
      "System.Security.Cryptography.h8x7kqmoa1.wasm": "System.Security.Cryptography.wasm",
      "System.Text.Encoding.CodePages.9pzppzi5rt.wasm": "System.Text.Encoding.CodePages.wasm",
      "System.Text.Encoding.Extensions.odbv26hjx3.wasm": "System.Text.Encoding.Extensions.wasm",
      "System.Text.Encodings.Web.kd0ajnxtf4.wasm": "System.Text.Encodings.Web.wasm",
      "System.Text.Json.4o1y0m7v38.wasm": "System.Text.Json.wasm",
      "System.Text.RegularExpressions.zcjh25fhag.wasm": "System.Text.RegularExpressions.wasm",
      "System.Threading.Channels.hbzpgsa7e5.wasm": "System.Threading.Channels.wasm",
      "System.Threading.r3pll6r9kf.wasm": "System.Threading.wasm",
      "System.Web.HttpUtility.vm548noc3p.wasm": "System.Web.HttpUtility.wasm",
      "System.Xml.Linq.53liyo777g.wasm": "System.Xml.Linq.wasm",
      "System.Xml.ReaderWriter.hjgg6qmu49.wasm": "System.Xml.ReaderWriter.wasm",
      "System.Xml.XDocument.75levxgv6x.wasm": "System.Xml.XDocument.wasm",
      "System.dqfxtvioy0.wasm": "System.wasm",
      "System.Private.CoreLib.bynjjq5609.wasm": "System.Private.CoreLib.wasm",
      "TTVLDashboard.CalendarLibrary.5ztvxanyn1.wasm": "TTVLDashboard.CalendarLibrary.wasm",
      "TTVLDashboard.SharedLibrary.6lbd7kopbj.wasm": "TTVLDashboard.SharedLibrary.wasm",
      "TTVLShareLibrary.bw63v05h2i.wasm": "TTVLShareLibrary.wasm",
      "TTVLWeb.Game.ymzensk1oa.wasm": "TTVLWeb.Game.wasm",
      "dotnet.js": "dotnet.js",
      "dotnet.native.l1ds2rhypd.js": "dotnet.native.js",
      "dotnet.native.etgrtk5jba.wasm": "dotnet.native.wasm",
      "dotnet.runtime.2hocyfcbj2.js": "dotnet.runtime.js",
      "icudt_CJK.tjcz0u77k5.dat": "icudt_CJK.dat",
      "icudt_EFIGS.tptq2av103.dat": "icudt_EFIGS.dat",
      "icudt_no_CJK.lfu7j35m59.dat": "icudt_no_CJK.dat"
    },
    "jsModuleNative": {
      "dotnet.native.l1ds2rhypd.js": "sha256-CU8oL4L0VAwGe3hCyxZDy7keJq9dcsWED0JKqrvlUb4="
    },
    "jsModuleRuntime": {
      "dotnet.runtime.2hocyfcbj2.js": "sha256-5oRcSUQSLbUYyq9jPgwB6domrDHYrvLX+53QxY+0y48="
    },
    "wasmNative": {
      "dotnet.native.etgrtk5jba.wasm": "sha256-HlUDSN0oXsH1WmjLNtyyvh9W0WQWWPGv3SJsHPJAwTE="
    },
    "icu": {
      "icudt_CJK.tjcz0u77k5.dat": "sha256-SZLtQnRc0JkwqHab0VUVP7T3uBPSeYzxzDnpxPpUnHk=",
      "icudt_EFIGS.tptq2av103.dat": "sha256-8fItetYY8kQ0ww6oxwTLiT3oXlBwHKumbeP2pRF4yTc=",
      "icudt_no_CJK.lfu7j35m59.dat": "sha256-L7sV7NEYP37/Qr2FPCePo5cJqRgTXRwGHuwF5Q+0Nfs="
    },
    "coreAssembly": {
      "System.Runtime.InteropServices.JavaScript.scprsuo250.wasm": "sha256-HI1L3LXaCLgFXx26TfH4FPR0Jc2WhemjetY64kkvMM0=",
      "System.Private.CoreLib.bynjjq5609.wasm": "sha256-/ZRBfSe0/4PVCtQmKEEdoIUIW8IFrrDb5qhcezJhONs="
    },
    "assembly": {
      "Blazored.LocalStorage.12n6dz54qr.wasm": "sha256-OaMAAd5n7ORfyur5e3QIyEVKJ76MKIvwbg7/icnnYcU=",
      "CurrieTechnologies.Razor.SweetAlert2.lvj7kgyo2r.wasm": "sha256-n6ubE26hJennNg6Gc9pr3BUMAuIS7CU4C94k2cw++m8=",
      "Ical.Net.anem8fmkmz.wasm": "sha256-WgiJRPLhomP0SBWCU2wuRjxmeJ+KyT702/Okg4gNQt0=",
      "Markdig.hc946gumly.wasm": "sha256-r5H+rUlGPpjyNTjRl9sPHtsy0fxPqCRow0c5r+XtBk8=",
      "Microsoft.AspNetCore.Authorization.cfbh8icicc.wasm": "sha256-GCSqZwcBw9c7YXdSM7PRVrO3kuNh04sDm+qACbYyDC4=",
      "Microsoft.AspNetCore.Components.6a500y5mh6.wasm": "sha256-Qk0oj+fCwtrdCeMl3NcghxKGypnbyzFVAzw1H+FPSA0=",
      "Microsoft.AspNetCore.Components.Authorization.8idgsl1q3y.wasm": "sha256-YEgltVhc+KdEEFJHVpA9zk0Nl5PNX9mJXGYRxBw9b1E=",
      "Microsoft.AspNetCore.Components.Forms.tro8u9xo1t.wasm": "sha256-aeHCyXxlKCRipIpX+xQN/AGNvM2pB5PEUoy7AUwuTuQ=",
      "Microsoft.AspNetCore.Components.Web.ieypenth0x.wasm": "sha256-ahSpZXMk/RcaiHEI+y83/QYQsi5yYMeTqXOuQXNcNGI=",
      "Microsoft.AspNetCore.Components.WebAssembly.cppeh7k1y5.wasm": "sha256-oCaa+C873dhsSnYC1LXaDOcgBiWHKfcfZWfiR7Y11Vo=",
      "Microsoft.AspNetCore.Connections.Abstractions.upo8amdyii.wasm": "sha256-3h4deASIsB3LPic+BaEWnxxbiw4O0P5L6iEiYWuPCMY=",
      "Microsoft.AspNetCore.Http.Connections.Client.ytkjx15092.wasm": "sha256-ylpdlrRaHymYvCU+JRP1VqHYo0y9C2LOiX0QbcMaCpc=",
      "Microsoft.AspNetCore.Http.Connections.Common.fanq0woy4f.wasm": "sha256-Z3gV/RzbS1M9PVLEHYJcnYLqIc93YfmKy+RGzNcZ688=",
      "Microsoft.AspNetCore.Metadata.kb2pnhxx9n.wasm": "sha256-AH1v+kDPbone1a2Uhs2EYvzbkEkxWfwLuPgetuVZVTA=",
      "Microsoft.AspNetCore.SignalR.Client.ck3fgmy7ic.wasm": "sha256-NDgLxfekSbraAZo+TlA8YsO2PzcaB/Cp+CASOl1OUr0=",
      "Microsoft.AspNetCore.SignalR.Client.Core.nmrfixdid2.wasm": "sha256-YQDv5Y67v0ucstcStTFcM0I0aC663LnltLErhkmEd4k=",
      "Microsoft.AspNetCore.SignalR.Common.vzsbdkzbkw.wasm": "sha256-i1RKU3LGZ9sZ3l5v9kxMePSXHTy2uSdUnxswOD9Km+s=",
      "Microsoft.AspNetCore.SignalR.Protocols.Json.vbb2g0mdls.wasm": "sha256-JarKzH1wC/D5onfkj4mjxRd4VQbSeyxJbJCzw3C8tHs=",
      "Microsoft.AspNetCore.WebUtilities.lvjk3wue0z.wasm": "sha256-oWSHWAWojRpwLO9Sipws7U6wYLbLpehQYdvb0BzMfK8=",
      "Microsoft.Extensions.Caching.Abstractions.8fsdtwddal.wasm": "sha256-3GFP1jfUWJPYAcd8T1YwK4YrJckULFWT1qgYHvbikk8=",
      "Microsoft.Extensions.Caching.Memory.q4n4ipze2x.wasm": "sha256-GlR3rbZAcjRGbMTwWNYPwZZAbpWo1iupv0v6vkcSFz4=",
      "Microsoft.Extensions.Configuration.vplowthuc6.wasm": "sha256-88c5kRcZGfMNHDgeKAeySnft5iGzItrdvO0CU0F5ugs=",
      "Microsoft.Extensions.Configuration.Abstractions.kpz8485frw.wasm": "sha256-yBqOQy2kaEM8ZQ6Z073yGmTFvTqMHdK8Egwfc3Z2wbo=",
      "Microsoft.Extensions.Configuration.Json.nplwh1dtgg.wasm": "sha256-65pm2RP/elQgQzD6nq5dU3SC9DK4WjVI8F/FAAPZN1M=",
      "Microsoft.Extensions.DependencyInjection.nm0fxb68vu.wasm": "sha256-ESLf6LVHQG/y70LByMHqpinNZqU1RImemsjw6aOs6gk=",
      "Microsoft.Extensions.DependencyInjection.Abstractions.vy92lhoa2e.wasm": "sha256-CUgtcf0Pyw3wFFQmQwQDiOAaZvWh82EsxXqazwgnqgo=",
      "Microsoft.Extensions.Diagnostics.lk2ttr0x6l.wasm": "sha256-u4RUZ6A9cWnQlgCP/S7IxI1Wh8+1iQrhwgBkYE0TEWo=",
      "Microsoft.Extensions.Diagnostics.Abstractions.o97u05c9gb.wasm": "sha256-tEtUKTeItXncbYJzaOn0W/BY6wHDdtVCzr0FPuKmN4M=",
      "Microsoft.Extensions.Features.mx2fvizm2n.wasm": "sha256-mnNLNUKU1Dx4kjiaQD5ke1iWMJAvo+neKW2vsaRaS/Y=",
      "Microsoft.Extensions.Http.b4829cflxg.wasm": "sha256-mx7WdlJbe1dB0H0C2pHyyFOwK/yDHY4xotKc9d/QPcY=",
      "Microsoft.Extensions.Localization.bvn14pws96.wasm": "sha256-6UgMJoVZBfDdfzYR0aKVK6BWArxpXC1qiQDDjiXw/L4=",
      "Microsoft.Extensions.Localization.Abstractions.ixsppbtym0.wasm": "sha256-tnMHqb6BpI1Jj9M9WNSAAJzzxHrQgov/aSXbFqc+xzk=",
      "Microsoft.Extensions.Logging.d5759dgs08.wasm": "sha256-cbD0gTzguX1Th+/5Z8fueACvOA2Fi3N3gAuQOyZMC2M=",
      "Microsoft.Extensions.Logging.Abstractions.32sdguicee.wasm": "sha256-SzfDERAOQN9b+xK22dm4Jq9wd1aqDz15wYc5of+5P7g=",
      "Microsoft.Extensions.Options.cye6fgpn51.wasm": "sha256-zG93jidCj4vBcVrLdr3CRtyNM05ws3tdBGjyDTdb9jQ=",
      "Microsoft.Extensions.Primitives.wdgxpgsqcr.wasm": "sha256-zPXs1ZxaGv/gjScqkSbos0m3HyxJufpF3haxdyuT0QA=",
      "Microsoft.JSInterop.0hi1zeigqe.wasm": "sha256-PNEDV+xipLuvR317S6a9u1afGzemESKRb3t3u2Wajts=",
      "Microsoft.JSInterop.WebAssembly.8eb000j8w7.wasm": "sha256-sGms9Oai1ztzgfMsqBvmeKwa5ZyGWr/AEXr6thw0lso=",
      "MudBlazor.bha5kpi6mp.wasm": "sha256-sQPDRAIxWtCPWerJkygPUzempXAsxfTnOfIb6iHrVtw=",
      "MudBlazor.Markdown.4m136gm5xx.wasm": "sha256-7NANmYGWTTJ6lIt2/od9Pn7ibuKfJr9JkzgsRkHasqQ=",
      "Newtonsoft.Json.jcjjiqe038.wasm": "sha256-s8KVuknfxWl1cuDvQM/OnpBfnpM1rxzvzq21S1cF36U=",
      "NodaTime.nqaqt3vwyv.wasm": "sha256-39HydYDp3jcrQXP93Z01k93WBdEJAqY4z2LGynXZ4zQ=",
      "System.Net.ServerSentEvents.nnx0l54pbx.wasm": "sha256-Y5OPE7A432suqRFQw6G/olPAphcD5/uOswnfRZ9tqLw=",
      "TimeZoneConverter.gpao39u6us.wasm": "sha256-zKwafr0zIwm7OrF1w2R8IO7TvPvQpDFf1UDiJfBACJQ=",
      "TinyMCE.Blazor.w2jy6xgyg6.wasm": "sha256-GP8+VJJNgYRrhBCGO4g8RhsLPRkoM6kHeR+ejWFnn8g=",
      "Microsoft.CSharp.g3k0wohq6w.wasm": "sha256-vHXcRMoaapQhfyDPl4F0n7RmlhxhkOtMrJhH5r6pShc=",
      "System.Collections.Concurrent.jt6m6ckwzx.wasm": "sha256-B4JVzR6UQ+cNpdxwCynTYeV0dJpJOQ1pkpuHh0BR9x0=",
      "System.Collections.Immutable.yi2oz8nx9e.wasm": "sha256-yvUIGjXoNLYq3mzb3gGWe+eQpuEpHdDlAFPndYLvn7o=",
      "System.Collections.NonGeneric.x9d02l8h8m.wasm": "sha256-NbltIWv8YdJGtoRYJaeAT0LtTUpz/gZYJI297+dIKM8=",
      "System.Collections.Specialized.ilumsknp4t.wasm": "sha256-ZmAZscUa2pFGGSbth2aH4uwD1YWOcfGc6scZ0L//1Ow=",
      "System.Collections.04nucowagr.wasm": "sha256-gMNq/QZ1HmTpcM7DPxrXR+T5XO1mpG9yiRhcw+564oM=",
      "System.ComponentModel.Annotations.f8jtdc89up.wasm": "sha256-YVzjcv41pkXtoX6i0OK0xNrLSsAloy5Wa03OxaSfEVI=",
      "System.ComponentModel.Primitives.ailars334u.wasm": "sha256-npnmRoPAcxzYxjkAuGVN29XFIdqndF8nuR6VwB8AbRI=",
      "System.ComponentModel.TypeConverter.4skrkh1bqm.wasm": "sha256-9OkWtBIBTylEEXIiVhMujwgcCj8nEXWw61U+nd088ys=",
      "System.ComponentModel.zy0ms90z2w.wasm": "sha256-a85hiaz30M0/9OUzRnieQICeSKptaNOBrkmVoGTwJMc=",
      "System.Console.9yrfyxte0s.wasm": "sha256-v+7R+QUxw3er4+FLqJZ39Gk63o0RxVFvPI5/MeK0kB8=",
      "System.Data.Common.9xt275crlm.wasm": "sha256-/R79zq8woDUZs31I57/yebw9/uZkzWG9PRpuMrqZLXc=",
      "System.Diagnostics.DiagnosticSource.xcz565ccv4.wasm": "sha256-vwNOaUS4oJzK0QlJcPCpunnwyh14fdpKyJbSkHFaCG4=",
      "System.Diagnostics.TraceSource.hu6e7hj53s.wasm": "sha256-KdXaN11vIetrLB2QkI4ptqTXIu89wjkp1Nugv5dk/y0=",
      "System.Drawing.Primitives.m5nrd9qy4x.wasm": "sha256-BkFbxv1I8Gi91w0amHcDVK8qokrPVZucalhRyHCi3iY=",
      "System.Drawing.l99g11my7u.wasm": "sha256-F0ixmpqMP1a51H1asGAs900AuBIeemTmM9goerykkVw=",
      "System.IO.Compression.sjtk9axw4l.wasm": "sha256-mPOgzqE+OctTBdml/6vlnwbFKQLtK4X9cQEv1K5Bn6A=",
      "System.IO.Pipelines.m2d449jl69.wasm": "sha256-LtM8m5jl1RwFoWRtkN18wN/5Axb4mnwWO10tM9S0MG4=",
      "System.Linq.Expressions.s0aletdlow.wasm": "sha256-/Jfhr+sHudt/mLutTdufcUskiR5H+zNF8Zkes4LGYcM=",
      "System.Linq.qrzytruudr.wasm": "sha256-ai2YHtgL6YXAVvWXJ7DqNBrQfTsnwAJKSfE0m1rSyZA=",
      "System.Memory.xnia7qknfj.wasm": "sha256-A3TQ0YCojgLAg7N5HyBFge6DkHNwqK18HZpPXff4SP8=",
      "System.Net.Http.Json.4oq6hi5mhk.wasm": "sha256-fCry+KkHOZ7kMu/tSjyMOhPlCiG13UmpNoljmvq6Jfo=",
      "System.Net.Http.42xwngdu5k.wasm": "sha256-XHYT14vpBl5yXumhDSvzhaMhgbvNBnjt7KlinPohVqE=",
      "System.Net.Primitives.zdik3pzjmm.wasm": "sha256-F3Fx/Oeg+/tgVfNJjEzVVSntARIkxmCU2TP6UrQ97B8=",
      "System.Net.Requests.yocwx48fyv.wasm": "sha256-vmbUhTaHHG+sRi3r7pWZyEizxfqnh7YfoxErGCU8UfY=",
      "System.Net.Security.qgtt234y95.wasm": "sha256-ltcJ+rRqUC6FOHnzNLXcii3/8SKFNWIL4b+JSXfYm+M=",
      "System.Net.WebSockets.Client.nixn8871fv.wasm": "sha256-kR4KXr8XWxGFAb16HM9M0pfmKkzl7gyeQUw6xkWUEIQ=",
      "System.Net.WebSockets.fn5g89hpim.wasm": "sha256-m5z2vojM70R2vyytX/IkoHF4ieQ44Jf6vHU1DUBW7WM=",
      "System.ObjectModel.v49pg873bw.wasm": "sha256-f1ogyW1igJ099QyysAXyUCUkETrE8WcitDF116Zr9iw=",
      "System.Private.Uri.7sunc304g0.wasm": "sha256-l3M9rb1IXAo4J5xhd/xXoSuJhXl9LLHwq+LcErb2lXk=",
      "System.Private.Xml.Linq.4428h436dt.wasm": "sha256-tK0nAjnYTcxGOdLEbL/MvtTnXHzjIKukjAuxabtqQAw=",
      "System.Private.Xml.8ut53fck6h.wasm": "sha256-sJqDgYGli96Yx9Xa3LZSk1JGGLyCCx9Xk8w2lIYkgwQ=",
      "System.Reflection.Emit.ILGeneration.mi2i2v6pwe.wasm": "sha256-Ppvw92GjR5ZMnhzI1ohmxQHVNqOAOLirjq5o30CETeo=",
      "System.Reflection.Emit.Lightweight.6xjxglsw9x.wasm": "sha256-Gid8ORv0tSY7i0YbIV4Uj/om+4LKxoSiv3SWya+jvNI=",
      "System.Reflection.Primitives.rm6pev6x7c.wasm": "sha256-0zdK1O2/G4xNaLMo2hC//dNPHchv0F0bgER1z22WxTU=",
      "System.Runtime.InteropServices.ukm0e9w85b.wasm": "sha256-TgR8Bg3UcfFPji+60WwsKCfuC2dzFP/ue/5+TApz7Pg=",
      "System.Runtime.Numerics.xqz3ca6hpg.wasm": "sha256-uWtGxxvjtxZCZlI5hmJYHaMqZngRvGqZIUf5RIDySXw=",
      "System.Runtime.Serialization.Formatters.3zc8j22ytb.wasm": "sha256-UTFCMYP/hm2uZeTO5h0clH/w8BkO+KGR+xj63bE5xJI=",
      "System.Runtime.Serialization.Primitives.zoxiyt80jv.wasm": "sha256-E/HAmN4M2+EonHFxa8YlUGJgPTqEkFWyO7Zju61aebo=",
      "System.Runtime.p2j64qg7s2.wasm": "sha256-EZKoUFGc71hGdmwRMEc8QnFWtid94VH/MPt7ESILu08=",
      "System.Security.Claims.ywb828g33q.wasm": "sha256-ru/qN4hy/2jhPOBcTtzMLPlN3dIH9WG7lcUmtyzGrD8=",
      "System.Security.Cryptography.h8x7kqmoa1.wasm": "sha256-AUBaC0+tysFZRMu1HoCLLyG9CVXKywZ/lOwxpLx/NTw=",
      "System.Text.Encoding.CodePages.9pzppzi5rt.wasm": "sha256-A/rSV0rJ5WSJ6dbam/eaaaiMcN930hZAIMCN3/bnzI4=",
      "System.Text.Encoding.Extensions.odbv26hjx3.wasm": "sha256-XDWVV1uxTX0E9cR9Uv0zCKx2ItX4bZfs8t+cSmZgXrI=",
      "System.Text.Encodings.Web.kd0ajnxtf4.wasm": "sha256-aB8QWDuMnJpSikgVmqsEKvRNFtgNCR8cFPGl2lNMWko=",
      "System.Text.Json.4o1y0m7v38.wasm": "sha256-DHtnjzsja5bVmf3NkEO7wOzAGfuTG7ucRznc0pUYGng=",
      "System.Text.RegularExpressions.zcjh25fhag.wasm": "sha256-vd2M0wraDP+r9I1r2hDVyuM3AYziAvBRJKBgC995PU4=",
      "System.Threading.Channels.hbzpgsa7e5.wasm": "sha256-Dd9CpGvjgJhoLFm7v7qM8KLTlzwpdgkPRXWWfhf130k=",
      "System.Threading.r3pll6r9kf.wasm": "sha256-V28QJLL4KopTBRuo8NsjmXNolMV+MC1AVBbQDCz5iVU=",
      "System.Web.HttpUtility.vm548noc3p.wasm": "sha256-hzkgfD6AX7sPkyB6bl6IeIFQKVln7DeYtP1cGLfmCH8=",
      "System.Xml.Linq.53liyo777g.wasm": "sha256-v9JHsJbBkO3lHVBoE7qJxiS0WfQzkxg+A8GpOWF+ls8=",
      "System.Xml.ReaderWriter.hjgg6qmu49.wasm": "sha256-vQV51bD26W4d9JATg0YIjNszHhK/1UgMaOrcKiL1rQQ=",
      "System.Xml.XDocument.75levxgv6x.wasm": "sha256-i8U4glWpuGMEh+O3BBgRUOr/HIGK3otm6Vb3FozG/1w=",
      "System.dqfxtvioy0.wasm": "sha256-5QZAjy4n7513fYxCXSXTsAkUmRsLiZ8m621Ot4k7FB0=",
      "TTVLDashboard.CalendarLibrary.5ztvxanyn1.wasm": "sha256-gcJYethVZqBhJpOF6KjyAtjL+4UEY9aeZTZnuwW2EAI=",
      "TTVLDashboard.SharedLibrary.6lbd7kopbj.wasm": "sha256-Fo1ZNAbZQRrc8Vgcxz0iJgJq/zbeqqdBYCqrv3BQe4I=",
      "TTVLShareLibrary.bw63v05h2i.wasm": "sha256-q1TUY6KSPeds5bYcaPM2MTLTAcG3UUBs25r7hizSCco=",
      "TTVLWeb.Game.ymzensk1oa.wasm": "sha256-6pI9LaON0iRjjQa4KudD6zmqp8QqMlKXdpz6mEeYkLc="
    },
    "libraryInitializers": {
      "_content/TinyMCE.Blazor/TinyMce.Blazor.lib.module.js": "sha256-YWo2eyD7vRsEwgJEvrAuzw9OkKV7xlijfLrNVtX4iWg="
    },
    "modulesAfterRuntimeReady": {
      "../_content/TinyMCE.Blazor/TinyMce.Blazor.lib.module.js": "sha256-YWo2eyD7vRsEwgJEvrAuzw9OkKV7xlijfLrNVtX4iWg="
    }
  },
  "cacheBootResources": true,
  "debugLevel": 0,
  "linkerEnabled": true,
  "appsettings": [
    "../appsettings.Development.json",
    "../appsettings.json"
  ],
  "globalizationMode": "sharded",
  "extensions": {
    "blazor": {}
  }
}